Circos-1.3.5.dist-info/DESCRIPTION.rst
Circos-1.3.5.dist-info/METADATA
Circos-1.3.5.dist-info/RECORD
Circos-1.3.5.dist-info/WHEEL
Circos-1.3.5.dist-info/metadata.json
Circos-1.3.5.dist-info/top_level.txt
circos/__init__.py
circos/circos.py
