Metadata-Version: 2.0
Name: Circos
Version: 1.3.5
Summary: Circos plots in Python!
Home-page: http://github.com/ericmjl/Circos
Author: Eric J. Ma, Justin Zabilansky, Jon Charest
Author-email: ericmajinglong@gmail.com
License: MIT
Keywords: network visualization,matplotlib,circos
Platform: UNKNOWN
Classifier: Topic :: Scientific/Engineering :: Visualization
Requires-Dist: matplotlib
Requires-Dist: numpy
Requires-Dist: pycodestyle
Requires-Dist: setuptools
